{"final_accuracy": 0.552, "timestamp": 1725360513, "checkpoint_dir_name": null, "done": false, "training_iteration": 1, "trial_id": "12a8d203", "date": "2024-09-03_12-48-33", "time_this_iter_s": 1604.7008259296417, "time_total_s": 1604.7008259296417, "pid": 118222, "hostname": "dl580-gpu3.unipi.it", "node_ip": "131.114.142.6", "config": {"strategy": {"regul": 0.0029203781816000323, "regul_last": 0.00014193499071197532, "alpha_ema": 0.23209128365265116, "alpha_ema_last": 0.03503334815620228, "lambda_": 0.1161688503013997, "clip": 1.6634214616665164}}, "time_since_restore": 1604.7008259296417, "iterations_since_restore": 1}
