{"final_accuracy": 0.539, "timestamp": 1726219697, "checkpoint_dir_name": null, "done": false, "training_iteration": 1, "trial_id": "743dfff5", "date": "2024-09-13_11-28-17", "time_this_iter_s": 3843.8716266155243, "time_total_s": 3843.8716266155243, "pid": 123028, "hostname": "dl580-gpu3.unipi.it", "node_ip": "131.114.142.6", "config": {"optimizer": {"lr": 0.022990702804988085}, "strategy": {"regul": 0.045778892320806605, "alpha_ema": 0.47789354049982585}}, "time_since_restore": 3843.8716266155243, "iterations_since_restore": 1}
