{"final_accuracy": 0.64, "timestamp": 1726191242, "checkpoint_dir_name": null, "done": false, "training_iteration": 1, "trial_id": "9aa0d147", "date": "2024-09-13_03-34-02", "time_this_iter_s": 624.5371956825256, "time_total_s": 624.5371956825256, "pid": 89345, "hostname": "dl580-gpu3.unipi.it", "node_ip": "131.114.142.6", "config": {"optimizer": {"lr": 0.0005466003969054791}, "strategy": {"regul": 5.5644430584803054e-05, "alpha_ema": 0.1008816297769003}}, "time_since_restore": 624.5371956825256, "iterations_since_restore": 1}
