{"final_accuracy": 0.056, "timestamp": 1725194620, "checkpoint_dir_name": null, "done": false, "training_iteration": 1, "trial_id": "e5522b07", "date": "2024-09-01_14-43-40", "time_this_iter_s": 2414.251852750778, "time_total_s": 2414.251852750778, "pid": 134742, "hostname": "dl580-gpu3.unipi.it", "node_ip": "131.114.142.6", "config": {"strategy": {"regul": 0.00026220501966171654, "alpha_ema": 0.3002641677918194, "lambda_": 0.06908858089646103, "clip": 0.601793286856839}}, "time_since_restore": 2414.251852750778, "iterations_since_restore": 1}
