{"final_accuracy": 0.53, "timestamp": 1724427580, "checkpoint_dir_name": null, "done": false, "training_iteration": 1, "trial_id": "7b5ae7f3", "date": "2024-08-23_17-39-40", "time_this_iter_s": 2334.986310482025, "time_total_s": 2334.986310482025, "pid": 28778, "hostname": "dl580-gpu3.unipi.it", "node_ip": "131.114.142.6", "config": {"optimizer": {"lr": 0.00039046117944939267}, "strategy": {"regul": 0.00973593096064762, "alpha_ema": 0.010953659130163279, "lambda_": 0.03701674966414102}}, "time_since_restore": 2334.986310482025, "iterations_since_restore": 1}
