{"final_accuracy": 0.518, "timestamp": 1726188750, "checkpoint_dir_name": null, "done": false, "training_iteration": 1, "trial_id": "70512220", "date": "2024-09-13_02-52-30", "time_this_iter_s": 622.4033212661743, "time_total_s": 622.4033212661743, "pid": 89937, "hostname": "dl580-gpu3.unipi.it", "node_ip": "131.114.142.6", "config": {"optimizer": {"lr": 0.007618055334189454}, "strategy": {"regul": 0.0004915152933040035, "alpha_ema": 0.12886182375002853}}, "time_since_restore": 622.4033212661743, "iterations_since_restore": 1}
