{"final_accuracy": 0.474, "timestamp": 1725194560, "checkpoint_dir_name": null, "done": false, "training_iteration": 1, "trial_id": "be0bb371", "date": "2024-09-01_14-42-40", "time_this_iter_s": 2408.0660738945007, "time_total_s": 2408.0660738945007, "pid": 133789, "hostname": "dl580-gpu3.unipi.it", "node_ip": "131.114.142.6", "config": {"strategy": {"regul": 0.8073742783571555, "alpha_ema": 0.018324956837977954, "lambda_": 0.29167388850383563, "clip": 2.9868131295691356}}, "time_since_restore": 2408.0660738945007, "iterations_since_restore": 1}
