{"final_accuracy": 0.522, "timestamp": 1726193785, "checkpoint_dir_name": null, "done": false, "training_iteration": 1, "trial_id": "e4982c49", "date": "2024-09-13_04-16-25", "time_this_iter_s": 627.5051798820496, "time_total_s": 627.5051798820496, "pid": 91782, "hostname": "dl580-gpu3.unipi.it", "node_ip": "131.114.142.6", "config": {"optimizer": {"lr": 8.479000887822517e-05}, "strategy": {"regul": 0.0026578916279191302, "alpha_ema": 0.39476419560538145}}, "time_since_restore": 627.5051798820496, "iterations_since_restore": 1}
