{"final_accuracy": 0.61, "timestamp": 1725502762, "checkpoint_dir_name": null, "done": false, "training_iteration": 1, "trial_id": "2abe1a86", "date": "2024-09-05_04-19-22", "time_this_iter_s": 2354.5315141677856, "time_total_s": 2354.5315141677856, "pid": 30718, "hostname": "dl580-gpu3.unipi.it", "node_ip": "131.114.142.6", "config": {"optimizer": {"lr": 0.0004540665442550957}, "strategy": {"regul": 0.0021060771598967734, "regul_last": 0.001791124195497525, "alpha_ema": 0.6325956136587844, "alpha_ema_last": 0.03730981629705019, "lambda_": 0.46113045673558334, "clip": 19282.08385073811}}, "time_since_restore": 2354.5315141677856, "iterations_since_restore": 1}
