{"final_accuracy": 0.504, "timestamp": 1725855998, "checkpoint_dir_name": null, "done": false, "training_iteration": 1, "trial_id": "3226f4ad", "date": "2024-09-09_06-26-38", "time_this_iter_s": 2347.1952245235443, "time_total_s": 2347.1952245235443, "pid": 44463, "hostname": "dl580-gpu3.unipi.it", "node_ip": "131.114.142.6", "config": {"optimizer": {"lr": 7.18532444635838e-05}, "strategy": {"regul": 0.0020180256664789854, "alpha_ema": 0.30735738072663077}}, "time_since_restore": 2347.1952245235443, "iterations_since_restore": 1}
