{"final_accuracy": 0.618, "timestamp": 1725351896, "checkpoint_dir_name": null, "done": false, "training_iteration": 1, "trial_id": "40af0f2f", "date": "2024-09-03_10-24-56", "time_this_iter_s": 2367.5713546276093, "time_total_s": 2367.5713546276093, "pid": 118628, "hostname": "dl580-gpu3.unipi.it", "node_ip": "131.114.142.6", "config": {"strategy": {"regul": 0.0030120034322185176, "regul_last": 0.014606416449854517, "alpha_ema": 0.16353108889631482, "alpha_ema_last": 0.2434982188506962, "lambda_": 1.4565085148137782, "clip": 0.5219850541569523}}, "time_since_restore": 2367.5713546276093, "iterations_since_restore": 1}
