{"final_accuracy": 0.1552, "timestamp": 1726643507, "checkpoint_dir_name": null, "done": false, "training_iteration": 1, "trial_id": "0cb614a1", "date": "2024-09-18_09-11-47", "time_this_iter_s": 5878.970663309097, "time_total_s": 5878.970663309097, "pid": 31161, "hostname": "dl580-gpu3.unipi.it", "node_ip": "131.114.142.6", "config": {"optimizer": {"lr": 3.72876895860001e-05}, "strategy": {"regul": 0.003977072777269227, "regul_last": 0.008061806512441302, "alpha_ema": 0.36960181916336565}}, "time_since_restore": 5878.970663309097, "iterations_since_restore": 1}
