{"final_accuracy": 0.588, "timestamp": 1719544257, "checkpoint_dir_name": null, "done": false, "training_iteration": 1, "trial_id": "acaf3dcb", "date": "2024-06-28_05-10-57", "time_this_iter_s": 2333.1171238422394, "time_total_s": 2333.1171238422394, "pid": 92754, "hostname": "dl580-gpu3.unipi.it", "node_ip": "131.114.142.6", "config": {"optimizer": {"lr": 5.039158173579176e-05}, "strategy": {"regul": 1.1512817792421095e-05, "alpha_ema": 0.049988142680922464}}, "time_since_restore": 2333.1171238422394, "iterations_since_restore": 1}
