{"final_accuracy": 0.609, "timestamp": 1726718571, "checkpoint_dir_name": null, "done": false, "training_iteration": 1, "trial_id": "3b67b062", "date": "2024-09-19_06-02-51", "time_this_iter_s": 3852.8271770477295, "time_total_s": 3852.8271770477295, "pid": 114331, "hostname": "dl580-gpu3.unipi.it", "node_ip": "131.114.142.6", "config": {"optimizer": {"lr": 0.00123309932755261}, "strategy": {"regul": 4.103792482487042e-05, "alpha_ema": 0.09032652654472355}}, "time_since_restore": 3852.8271770477295, "iterations_since_restore": 1}
