{"final_accuracy": 0.62, "timestamp": 1718411912, "checkpoint_dir_name": null, "done": false, "training_iteration": 1, "trial_id": "9782988a", "date": "2024-06-15_02-38-32", "time_this_iter_s": 2359.9205873012543, "time_total_s": 2359.9205873012543, "pid": 81905, "hostname": "dl580-gpu3.unipi.it", "node_ip": "131.114.142.6", "config": {"optimizer": {"lr": 0.00024238261746148377}, "strategy": {"regul": 6.0406076392375496e-05}}, "time_since_restore": 2359.9205873012543, "iterations_since_restore": 1}
