{"final_accuracy": 0.52, "timestamp": 1725844237, "checkpoint_dir_name": null, "done": false, "training_iteration": 1, "trial_id": "efd4f986", "date": "2024-09-09_03-10-37", "time_this_iter_s": 2334.007168531418, "time_total_s": 2334.007168531418, "pid": 44052, "hostname": "dl580-gpu3.unipi.it", "node_ip": "131.114.142.6", "config": {"optimizer": {"lr": 0.004230076898385823}, "strategy": {"regul": 0.00023819894930713947, "alpha_ema": 0.09900369429720995}}, "time_since_restore": 2334.007168531418, "iterations_since_restore": 1}
