{"final_accuracy": 0.57, "timestamp": 1721431277, "checkpoint_dir_name": null, "done": false, "training_iteration": 1, "trial_id": "4d9e0a0b", "date": "2024-07-20_01-21-17", "time_this_iter_s": 2340.2710320949554, "time_total_s": 2340.2710320949554, "pid": 93331, "hostname": "dl580-gpu3.unipi.it", "node_ip": "131.114.142.6", "config": {"optimizer": {"lr": 0.0015581821221547457}, "strategy": {"regul": 0.01158189123869917, "alpha_ema": 0.21255340796809064}}, "time_since_restore": 2340.2710320949554, "iterations_since_restore": 1}
