{"final_accuracy": 0.3464, "timestamp": 1726637607, "checkpoint_dir_name": null, "done": false, "training_iteration": 1, "trial_id": "76946b40", "date": "2024-09-18_07-33-27", "time_this_iter_s": 5883.024739742279, "time_total_s": 5883.024739742279, "pid": 30260, "hostname": "dl580-gpu3.unipi.it", "node_ip": "131.114.142.6", "config": {"optimizer": {"lr": 0.005055906595820116}, "strategy": {"regul": 0.006594110956165557, "regul_last": 0.03188973180926783, "alpha_ema": 0.04177311869590432}}, "time_since_restore": 5883.024739742279, "iterations_since_restore": 1}
